[{"name":"Desert Lanes Bowling Center","phone":"8307578065","twitter":"desertlanes","address":"3515 El Indio Hwy","lat":28.67746718644098,"lng":-100.46228752764463,"city_fetched":"Eagle Pass","state":"TX","country":"United States","canonicalUrl":"https://foursquare.com/v/desert-lanes-bowling-center/4e066b62fa767637fd24cd81","category":"Bowling Alley","checkinsCount":132,"usersCount":124,"tipCount":2,"visitsCount":208,"url":"http://www.desertlanes.com","tier":"","message":"","currency":"","rating":6.2},{"name":"Th3 Draft","lat":28.706457,"lng":-100.483072,"city_fetched":"Eagle Pass","state":"TX","country":"United States","canonicalUrl":"https://foursquare.com/v/th3-draft/4e59b72d1f6e804280ca8e10","category":"Bar","checkinsCount":271,"usersCount":137,"tipCount":3,"visitsCount":278,"tier":"","message":"","currency":"","rating":5.9}]