[{"name":"Mosey's","phone":"8502150425","twitter":"moseysdowntown","address":"425 Grace Ave","lat":30.15600793326056,"lng":-85.66159112763447,"city_fetched":"Panama City","state":"FL","country":"United States","canonicalUrl":"https://foursquare.com/v/moseys/5436ded8498e1891c570da96","category":"Bar","checkinsCount":94,"usersCount":48,"tipCount":2,"visitsCount":142,"tier":"","message":"","currency":"","rating":8.2},{"name":"TGI Fridays","phone":"8507471861","twitter":"tgifridays","address":"1022 W 23 Rd St","lat":30.19021376,"lng":-85.67731465,"city_fetched":"Panama City","state":"FL","country":"United States","canonicalUrl":"https://foursquare.com/v/tgi-fridays/4b9a825af964a52024bc35e3","category":"American Restaurant","checkinsCount":3104,"usersCount":861,"tipCount":17,"visitsCount":3580,"url":"http://tgifridays.com","tier":2,"message":"Moderate","currency":"$","rating":7.7},{"name":"Beef 'O' Brady's","phone":"8502710064","twitter":"beefobrady","address":"2310 S Highway 77 #350","lat":30.223597613146616,"lng":-85.65106104388373,"city_fetched":"Panama City","state":"FL","country":"United States","canonicalUrl":"https://foursquare.com/v/beef-o-bradys/4b75ff8cf964a52070352ee3","category":"Pub","checkinsCount":1136,"usersCount":460,"tipCount":8,"visitsCount":1323,"url":"http://www.beefobradys.com","tier":"","message":"","currency":"","rating":7.6},{"name":"Pelican's Bar & Grill","phone":"8502366076","twitter":"baypointresort","address":"4114 Jan Cooley Dr","lat":30.136151085334472,"lng":-85.72470277783653,"city_fetched":"Panama City","state":"FL","country":"United States","canonicalUrl":"https://foursquare.com/v/pelicans-bar--grill/4bbbc0ede5b0d13a3d7d6e7c","category":"Seafood Restaurant","checkinsCount":535,"usersCount":265,"tipCount":15,"visitsCount":541,"url":"http://www.baypointresorts.com","tier":2,"message":"Moderate","currency":"$","rating":7.3},{"name":"No Name Lounge","phone":"8507639153","address":"5555 W Highway 98","lat":30.185980008043476,"lng":-85.73444682633428,"city_fetched":"Panama City","state":"FL","country":"United States","canonicalUrl":"https://foursquare.com/v/no-name-lounge/4d1bf5621356224b45b40bbe","category":"Dive Bar","checkinsCount":1517,"usersCount":496,"tipCount":7,"visitsCount":1584,"tier":"","message":"","currency":"","rating":7.2},{"name":"Blue Moon Bar & Grille","phone":"8502718866","lat":30.237097358169947,"lng":-85.65250096392401,"city_fetched":"Panama City","state":"FL","country":"United States","canonicalUrl":"https://foursquare.com/v/blue-moon-bar--grille/4e3dab9118a83d5b2847cf2f","category":"Bar","checkinsCount":503,"usersCount":116,"tipCount":5,"visitsCount":572,"tier":"","message":"","currency":"","rating":7.1},{"name":"The Wine Dog","phone":"8507856835","address":"103 W 23rd St","lat":30.18954,"lng":-85.66175,"city_fetched":"Panama City","state":"FL","country":"United States","canonicalUrl":"https://foursquare.com/v/the-wine-dog/4e14caedc65bedaeefc0a1ec","category":"Wine Bar","checkinsCount":210,"usersCount":83,"tipCount":3,"visitsCount":210,"url":"http://www.thewinedog.net","tier":"","message":"","currency":"","rating":6.8},{"name":"The Watershed","address":"1118 Bayview Ave","lat":30.169090519875766,"lng":-85.7025026961357,"city_fetched":"Panama City","state":"FL","country":"United States","canonicalUrl":"https://foursquare.com/v/the-watershed/4cbc6189558576b0a1a74a0e","category":"Bar","checkinsCount":480,"usersCount":161,"tipCount":4,"visitsCount":482,"tier":"","message":"","currency":"","rating":6.4},{"name":"Player's Saloon","address":"4300 Highway 98","lat":30.181200102429667,"lng":-85.71650035516753,"city_fetched":"Panama City","state":"FL","country":"United States","canonicalUrl":"https://foursquare.com/v/players-saloon/519712e6498e336c7bdcb338","category":"Bar","checkinsCount":201,"usersCount":89,"tipCount":2,"visitsCount":268,"tier":"","message":"","currency":"","rating":6.2},{"name":"Gracie Rae Bar and Grill","phone":"8507858761","address":"1201 Beck Ave","lat":30.17012147737671,"lng":-85.70273326396665,"city_fetched":"Panama City","state":"FL","country":"United States","canonicalUrl":"https://foursquare.com/v/gracie-rae-bar-and-grill/4b9858e6f964a5201f3d35e3","category":"Bar","checkinsCount":971,"usersCount":512,"tipCount":13,"visitsCount":974,"url":"http://gracierae.theshrimpboatrestaurant.com","tier":"","message":"","currency":"","rating":5.9},{"name":"The Buccaneer Bar and Grill","phone":"8506401828","address":"711 W Beach Dr","lat":30.159160065105535,"lng":-85.66936068184485,"city_fetched":"Panama City","state":"FL","country":"United States","canonicalUrl":"https://foursquare.com/v/the-buccaneer-bar-and-grill/4c1a736fb4e62d7f16d4d793","category":"Bar","checkinsCount":411,"usersCount":237,"tipCount":3,"visitsCount":534,"url":"http://buccaneerbeachmotel.com","tier":"","message":"","currency":"","rating":5.7}]